ephor_sdk_1_sdk/__init__.py
ephor_sdk_1_sdk/api_client.py
ephor_sdk_1_sdk/api_response.py
ephor_sdk_1_sdk/configuration.py
ephor_sdk_1_sdk/exceptions.py
ephor_sdk_1_sdk/py.typed
ephor_sdk_1_sdk/rest.py
ephor_sdk_1_sdk/api/__init__.py
ephor_sdk_1_sdk/api/gifs_api.py
ephor_sdk_1_sdk/api/stickers_api.py
ephor_sdk_1_sdk/models/__init__.py
ephor_sdk_1_sdk/models/get_gifs_by_id200_response.py
ephor_sdk_1_sdk/models/gif.py
ephor_sdk_1_sdk/models/gif_images.py
ephor_sdk_1_sdk/models/gif_images_downsized.py
ephor_sdk_1_sdk/models/gif_images_downsized_large.py
ephor_sdk_1_sdk/models/gif_images_downsized_medium.py
ephor_sdk_1_sdk/models/gif_images_downsized_small.py
ephor_sdk_1_sdk/models/gif_images_downsized_still.py
ephor_sdk_1_sdk/models/gif_images_fixed_height.py
ephor_sdk_1_sdk/models/gif_images_fixed_height_downsampled.py
ephor_sdk_1_sdk/models/gif_images_fixed_height_small.py
ephor_sdk_1_sdk/models/gif_images_fixed_height_small_still.py
ephor_sdk_1_sdk/models/gif_images_fixed_height_still.py
ephor_sdk_1_sdk/models/gif_images_fixed_width.py
ephor_sdk_1_sdk/models/gif_images_fixed_width_downsampled.py
ephor_sdk_1_sdk/models/gif_images_fixed_width_small.py
ephor_sdk_1_sdk/models/gif_images_fixed_width_small_still.py
ephor_sdk_1_sdk/models/gif_images_fixed_width_still.py
ephor_sdk_1_sdk/models/gif_images_looping.py
ephor_sdk_1_sdk/models/gif_images_original.py
ephor_sdk_1_sdk/models/gif_images_original_still.py
ephor_sdk_1_sdk/models/gif_images_preview.py
ephor_sdk_1_sdk/models/gif_images_preview_gif.py
ephor_sdk_1_sdk/models/image.py
ephor_sdk_1_sdk/models/meta.py
ephor_sdk_1_sdk/models/pagination.py
ephor_sdk_1_sdk/models/random_gif200_response.py
ephor_sdk_1_sdk/models/user.py
ephor_sdk_1_sdk-0.0.1.dist-info/METADATA
ephor_sdk_1_sdk-0.0.1.dist-info/WHEEL
ephor_sdk_1_sdk-0.0.1.dist-info/top_level.txt
ephor_sdk_1_sdk-0.0.1.dist-info/RECORD
